hmd_cli_python/__init__.py
hmd_cli_python/controller.py
hmd_cli_python/hmd_cli_python.py
hmd_cli_python-0.2.115.dist-info/METADATA
hmd_cli_python-0.2.115.dist-info/WHEEL
hmd_cli_python-0.2.115.dist-info/top_level.txt
hmd_cli_python-0.2.115.dist-info/RECORD
