Metadata-Version: 2.1
Name: hmd-cli-python
Version: 0.2.115
Summary: Implementation for python cli command
Author: Jim Majure
Author-email: jim.majure@hmdlabs.io
License: Apache 2.0
Requires-Dist: attrs==24.2.0
Requires-Dist: aws-secretsmanager-caching==1.1.3
Requires-Dist: backports-tarfile==1.2.0
Requires-Dist: boto3==1.36.22
Requires-Dist: botocore==1.36.23
Requires-Dist: build==1.2.2.post1
Requires-Dist: cachetools==5.2.0
Requires-Dist: cement==3.0.6
Requires-Dist: certifi==2025.4.26
Requires-Dist: cffi==2.0.0
Requires-Dist: charset-normalizer==2.0.12
Requires-Dist: click==8.1.8
Requires-Dist: colorlog==6.6.0
Requires-Dist: coverage[toml]==7.8.0
Requires-Dist: cryptography==46.0.2
Requires-Dist: docutils==0.21.2
Requires-Dist: durationpy==0.10
Requires-Dist: google-auth==2.9.1
Requires-Dist: hmd-cli-app~=1.2.616
Requires-Dist: hmd-cli-tools~=1.2.242
Requires-Dist: id==1.5.0
Requires-Dist: idna==3.10
Requires-Dist: importlib-metadata==8.7.0
Requires-Dist: iniconfig==2.1.0
Requires-Dist: inquirerpy==0.3.4
Requires-Dist: jaraco-classes==3.4.0
Requires-Dist: jaraco-context==6.0.1
Requires-Dist: jaraco-functools==4.1.0
Requires-Dist: jeepney==0.9.0
Requires-Dist: jinja2==3.1.6
Requires-Dist: jmespath==0.10.0
Requires-Dist: keyring==25.6.0
Requires-Dist: kubernetes==34.1.0
Requires-Dist: markdown-it-py==3.0.0
Requires-Dist: markupsafe==3.0.2
Requires-Dist: mdurl==0.1.2
Requires-Dist: more-itertools==10.7.0
Requires-Dist: nh3==0.2.21
Requires-Dist: oauthlib==3.3.1
Requires-Dist: packaging==25.0
Requires-Dist: pfzy==0.3.4
Requires-Dist: pip-compile-multi==3.2.2
Requires-Dist: pip-tools==7.4.1
Requires-Dist: pluggy==1.5.0
Requires-Dist: prompt-toolkit==3.0.38
Requires-Dist: py==1.11.0
Requires-Dist: pyasn1==0.6.1
Requires-Dist: pyasn1-modules==0.4.2
Requires-Dist: pycparser==2.23
Requires-Dist: pygments==2.19.1
Requires-Dist: pyproject-hooks==1.2.0
Requires-Dist: pytest==7.0.1
Requires-Dist: pytest-cov==3.0.0
Requires-Dist: python-dateutil==2.8.2
Requires-Dist: python-dotenv==1.1.1
Requires-Dist: pyyaml==6.0.1
Requires-Dist: readme-renderer==44.0
Requires-Dist: requests==2.32.3
Requires-Dist: requests-oauthlib==1.3.1
Requires-Dist: requests-toolbelt==1.0.0
Requires-Dist: rfc3986==2.0.0
Requires-Dist: rich==14.0.0
Requires-Dist: rsa==4.8
Requires-Dist: s3transfer==0.11.2
Requires-Dist: secretstorage==3.3.3
Requires-Dist: six==1.16.0
Requires-Dist: tomli==2.2.1
Requires-Dist: toposort==1.10
Requires-Dist: twine==6.1.0
Requires-Dist: urllib3==1.26.8
Requires-Dist: wcwidth==0.2.6
Requires-Dist: websocket-client==1.3.3
Requires-Dist: wheel==0.45.1
Requires-Dist: zipp==3.21.0
